ntfy_api/__init__.py
ntfy_api/_internals.py
ntfy_api/actions.py
ntfy_api/enums.py
ntfy_api/message.py
ntfy_api/publisher.py
ntfy_api-0.0.6.dist-info/LICENSE
ntfy_api-0.0.6.dist-info/METADATA
ntfy_api-0.0.6.dist-info/WHEEL
ntfy_api-0.0.6.dist-info/top_level.txt
ntfy_api-0.0.6.dist-info/RECORD
