Metadata-Version: 2.1
Name: ntfy-api
Version: 0.0.6
Summary: A Python wrapper around the ntfy API.
Author-email: Tanner Corcoran <tannerbcorcoran@gmail.com>
Maintainer-email: Tanner Corcoran <tannerbcorcoran@gmail.com>
License: Apache 2.0
Project-URL: Homepage, https://github.com/tanrbobanr/ntfy-api
Project-URL: Documentation, https://github.com/tanrbobanr/ntfy-api/blob/main/README.md
Project-URL: Changelog, https://github.com/tanrbobanr/ntfy-api/blob/main/CHANGELOG.md
Project-URL: License, https://github.com/tanrbobanr/ntfy-api/blob/main/LICENSE
Project-URL: Source, https://github.com/tanrbobanr/ntfy-api
Project-URL: Bug Tracker, https://github.com/tanrbobanr/ntfy-api/issues
Keywords: ntfy,nfty API
Classifier: Development Status :: 3 - Alpha
Classifier: Operating System :: OS Independent
Classifier: Programming Language :: Python
Classifier: Programming Language :: Python :: 3
Classifier: Programming Language :: Python :: 3 :: Only
Classifier: Programming Language :: Python :: 3.9
Classifier: Programming Language :: Python :: 3.10
Classifier: Programming Language :: Python :: 3.11
Classifier: Programming Language :: Python :: 3.12
Classifier: Programming Language :: Python :: 3.13
Classifier: Programming Language :: Python :: 3.14
Classifier: Topic :: Software Development
Classifier: Topic :: Software Development :: Libraries
Classifier: Typing :: Typed
Classifier: Topic :: Utilities
Classifier: Intended Audience :: Developers
Classifier: License :: OSI Approved :: Apache Software License
Requires-Python: >=3.9
License-File: LICENSE
Requires-Dist: httpx
Requires-Dist: typing-extensions >=4.5.0 ; python_version < "3.12"
